nekograd/__init__.py
nekograd/__version__.py
nekograd/utils.py
nekograd/data/__init__.py
nekograd/data/split.py
nekograd/metrics/__init__.py
nekograd/metrics/binary.py
nekograd/metrics/checks.py
nekograd/metrics/utils.py
nekograd/model/__init__.py
nekograd/model/base.py
nekograd/model/callbacks.py
nekograd/model/commands.py
nekograd/model/model.py
nekograd/model/policy.py
nekograd/model/utils.py
nekograd/torch/__init__.py
nekograd/torch/criterion.py
nekograd/torch/utils.py
nekograd-0.2.0.dist-info/LICENSE
nekograd-0.2.0.dist-info/METADATA
nekograd-0.2.0.dist-info/WHEEL
nekograd-0.2.0.dist-info/top_level.txt
nekograd-0.2.0.dist-info/RECORD
