Metadata-Version: 2.1
Name: nekograd
Version: 0.2.0
Home-page: https://github.com/arseniybelkov/nekograd
License: MIT
Requires-Python: >=3.7
License-File: LICENSE
Requires-Dist: numpy
Requires-Dist: pandas
Requires-Dist: scikit-learn
Requires-Dist: scikit-image
Requires-Dist: torch
Requires-Dist: pytorch-lightning
Requires-Dist: tensorboardX
Requires-Dist: cytoolz
Requires-Dist: more-itertools
